keksik_api/__init__.py
keksik_api/api.py
keksik_api/base.py
keksik_api/callback/__init__.py
keksik_api/callback/callback.py
keksik_api/callback/handler.py
keksik_api/callback/router.py
keksik_api/callback/rules.py
keksik_api/exceptions.py
keksik_api/methods/__init__.py
keksik_api/methods/base.py
keksik_api/methods/campaigns.py
keksik_api/methods/donates.py
keksik_api/methods/payments.py
keksik_api/schemas/__init__.py
keksik_api/schemas/base.py
keksik_api/schemas/campaigns.py
keksik_api/schemas/donates.py
keksik_api/schemas/events.py
keksik_api/schemas/payments.py
keksik_api-0.2.5.dist-info/LICENSE
keksik_api-0.2.5.dist-info/METADATA
keksik_api-0.2.5.dist-info/WHEEL
keksik_api-0.2.5.dist-info/RECORD
