Metadata-Version: 2.1
Name: keksik-api
Version: 0.2.5
Summary: Обвертка над API keksik.io
Home-page: https://github.com/lordralinc/keksik_api
License: MIT
Author: lordralinc
Author-email: lordralinc@gmail.com
Requires-Python: >=3.8,<4.0
Classifier: License :: OSI Approved :: MIT License
Classifier: Programming Language :: Python :: 3
Classifier: Programming Language :: Python :: 3.8
Classifier: Programming Language :: Python :: 3.9
Classifier: Programming Language :: Python :: 3.10
Classifier: Programming Language :: Python :: 3.11
Requires-Dist: aiohttp (>=3.8,<4.0)
Requires-Dist: pydantic (>=1.0,<3.0)
Project-URL: Repository, https://github.com/lordralinc/keksik_api
